nws_wwa/__init__.py
nws_wwa/cli.py
nws_wwa-0.0.5.dist-info/LICENSE
nws_wwa-0.0.5.dist-info/METADATA
nws_wwa-0.0.5.dist-info/WHEEL
nws_wwa-0.0.5.dist-info/entry_points.txt
nws_wwa-0.0.5.dist-info/top_level.txt
nws_wwa-0.0.5.dist-info/RECORD
