Metadata-Version: 2.1
Name: nws-wwa
Version: 0.0.5
Summary: Download watch, warning and advisory data from the National Weather Service
Home-page: http://www.github.com/datadesk/nws-wwa
Author: Ben Welsh
Author-email: b@palewi.re
License: MIT
Project-URL: Maintainer, https://github.com/datadesk
Project-URL: Source, https://github.com/datadesk/nws-wwa
Project-URL: Tracker, https://github.com/datadesk/nws-wwa/issues
Classifier: Development Status :: 5 - Production/Stable
Classifier: Programming Language :: Python
Classifier: Programming Language :: Python :: 3.9
Classifier: Programming Language :: Python :: 3.10
Classifier: Programming Language :: Python :: 3.11
Classifier: License :: OSI Approved :: MIT License
License-File: LICENSE
Requires-Dist: requests
Requires-Dist: fiona
Requires-Dist: geojson
Requires-Dist: click
Requires-Dist: exceptiongroup
